mongoengine_mls.py
mongoengine_mls-1.1.0.dist-info/WHEEL
mongoengine_mls-1.1.0.dist-info/top_level.txt
mongoengine_mls-1.1.0.dist-info/metadata.json
mongoengine_mls-1.1.0.dist-info/RECORD
mongoengine_mls-1.1.0.dist-info/DESCRIPTION.rst
mongoengine_mls-1.1.0.dist-info/METADATA
