Metadata-Version: 2.0
Name: mongoengine-mls
Version: 1.1.0
Summary: MultiLingualField for MongoEngine
Home-page: https://github.com/rembish/mongoengine-mls
Author: Aleksey Rembish
Author-email: alex@rembish.org
License: BSD
Platform: UNKNOWN
Classifier: Development Status :: 5 - Production/Stable
Classifier: License :: OSI Approved :: BSD License
Classifier: Programming Language :: Python :: 2
Classifier: Programming Language :: Python :: 2.6
Classifier: Programming Language :: Python :: 2.7
Classifier: Programming Language :: Python :: 3
Classifier: Programming Language :: Python :: 3.2
Classifier: Programming Language :: Python :: 3.3
Classifier: Programming Language :: Python :: 3.4
Classifier: Programming Language :: Python :: Implementation :: PyPy
Classifier: Topic :: Software Development :: Internationalization
Classifier: Topic :: Software Development :: Libraries :: Python Modules
Classifier: Topic :: Utilities
Requires-Dist: mongoengine
Requires-Dist: mls
Requires-Dist: pymongo (<3.0)
